streamstats_access/__init__.py
streamstats_access/api_client.py
streamstats_access/batch_query.py
streamstats_access/config.json
streamstats_access/config.py
streamstats_access/endpoints.py
streamstats_access/models.py
streamstats_access/utils.py
streamstats_access-0.1.9.dist-info/LICENSE
streamstats_access-0.1.9.dist-info/METADATA
streamstats_access-0.1.9.dist-info/WHEEL
streamstats_access-0.1.9.dist-info/top_level.txt
streamstats_access-0.1.9.dist-info/RECORD
