Metadata-Version: 2.1
Name: streamstats_access
Version: 0.1.9
Summary: A Python package to access and process data from the USGS StreamStats API.
Author-email: Scott Lawson <scott.lawson@uvm.edu>
License: MIT License
Project-URL: Homepage, https://github.com/sclaw/streamstats_access
Project-URL: Bug Tracker, https://github.com/sclaw/streamstats_access/issues
Keywords: USGS,StreamStats,API,Geospatial,Hydrology,statistics,watershed characteristics,water resources,data retrieval
Classifier: Development Status :: 4 - Beta
Classifier: Intended Audience :: Science/Research
Classifier: License :: OSI Approved :: MIT License
Classifier: Programming Language :: Python :: 3
Classifier: Programming Language :: Python :: 3.7
Classifier: Programming Language :: Python :: 3.8
Classifier: Programming Language :: Python :: 3.9
Classifier: Programming Language :: Python :: 3.10
Classifier: Topic :: Scientific/Engineering :: GIS
License-File: LICENSE
Requires-Dist: aiohttp >=3.8.1
Requires-Dist: geopandas >=0.9.0
Requires-Dist: pandas >=1.3.0
Provides-Extra: dev
Requires-Dist: twine ; extra == 'dev'
Requires-Dist: build ; extra == 'dev'
